LICENSE
MANIFEST.in
README.md
setup.py
dataframe_image/__init__.py
dataframe_image/_browser_pdf.py
dataframe_image/_bundler.py
dataframe_image/_command_line.py
dataframe_image/_convert.py
dataframe_image/_latex_pdf.py
dataframe_image/_matplotlib_table.py
dataframe_image/_my_asyncio.py
dataframe_image/_pandas_accessor.py
dataframe_image/_preprocessors.py
dataframe_image/_screenshot.py
dataframe_image/static/download.html
dataframe_image/static/fail.html
dataframe_image/static/form.html
dataframe_image/static/style.css
dataframe_image_cn.egg-info/PKG-INFO
dataframe_image_cn.egg-info/SOURCES.txt
dataframe_image_cn.egg-info/dependency_links.txt
dataframe_image_cn.egg-info/entry_points.txt
dataframe_image_cn.egg-info/requires.txt
dataframe_image_cn.egg-info/top_level.txt
jupyter-config/nbconfig/notebook.d/dataframe_image.json
tests/__init__.py
tests/delete_test_results.py
tests/test_convert.py
tests/test_df_image.py