Metadata-Version: 2.1
Name: dataframe-image-cn
Version: 0.1.1
Summary: Embed pandas DataFrames as images in pdf and markdown files when converting from Jupyter Notebooks (Use font SimHei)
Home-page: https://github.com/aslan9/dataframe_image
Author: Puyuan Tech
Author-email: jch@puyuan.tech
License: MIT
Keywords: jupyter notebook pandas dataframe image pdf markdown
Platform: UNKNOWN
Classifier: Programming Language :: Python :: 3
Classifier: License :: OSI Approved :: MIT License
Classifier: Operating System :: OS Independent
Requires-Python: >=3.6
License-File: LICENSE
